whisper_vtt2srt/__init__.py
whisper_vtt2srt/__main__.py
whisper_vtt2srt/main.py
whisper_vtt2srt/adapters/__init__.py
whisper_vtt2srt/adapters/parsers.py
whisper_vtt2srt/adapters/writers.py
whisper_vtt2srt/domain/__init__.py
whisper_vtt2srt/domain/interfaces.py
whisper_vtt2srt/domain/models.py
whisper_vtt2srt/domain/options.py
whisper_vtt2srt/use_cases/__init__.py
whisper_vtt2srt/use_cases/batch.py
whisper_vtt2srt/use_cases/filters.py
whisper_vtt2srt/use_cases/pipeline.py
whisper_vtt2srt-0.1.2.dist-info/licenses/LICENSE
whisper_vtt2srt-0.1.2.dist-info/METADATA
whisper_vtt2srt-0.1.2.dist-info/WHEEL
whisper_vtt2srt-0.1.2.dist-info/entry_points.txt
whisper_vtt2srt-0.1.2.dist-info/top_level.txt
whisper_vtt2srt-0.1.2.dist-info/RECORD
