Metadata-Version: 2.4
Name: whisper-vtt2srt
Version: 0.1.2
Summary: A professional, robust library for converting WebVTT to SRT with advanced cleaning capabilities for AI-generated subtitles.
Author-email: Jorcelino Junior <jorcelino@live.com>
License: MIT
Project-URL: Homepage, https://github.com/jorcelinojunior/whisper-vtt2srt
Project-URL: Bug Tracker, https://github.com/jorcelinojunior/whisper-vtt2srt/issues
Classifier: Programming Language :: Python :: 3
Classifier: License :: OSI Approved :: MIT License
Classifier: Operating System :: OS Independent
Classifier: Topic :: Multimedia :: Video
Classifier: Topic :: Text Processing :: Filters
Requires-Python: >=3.10
License-File: LICENSE
Provides-Extra: dev
Requires-Dist: pytest>=7.0; extra == "dev"
Requires-Dist: black; extra == "dev"
Requires-Dist: ruff; extra == "dev"
Requires-Dist: mypy; extra == "dev"
Requires-Dist: build; extra == "dev"
Provides-Extra: docs
Requires-Dist: mkdocs>=1.5; extra == "docs"
Requires-Dist: mkdocs-material>=9.0; extra == "docs"
Requires-Dist: mkdocstrings[python]>=0.24; extra == "docs"
Dynamic: license-file
